CHANGES.rst
CONTRIBUTORS.rst
MANIFEST.in
README.rst
setup.py
src/collective/__init__.py
src/collective.saconnect.egg-info/PKG-INFO
src/collective.saconnect.egg-info/SOURCES.txt
src/collective.saconnect.egg-info/dependency_links.txt
src/collective.saconnect.egg-info/entry_points.txt
src/collective.saconnect.egg-info/namespace_packages.txt
src/collective.saconnect.egg-info/not-zip-safe
src/collective.saconnect.egg-info/requires.txt
src/collective.saconnect.egg-info/top_level.txt
src/collective/saconnect/__init__.py
src/collective/saconnect/configure.zcml
src/collective/saconnect/genericsetup.py
src/collective/saconnect/interfaces.py
src/collective/saconnect/saconfig.py
src/collective/saconnect/storage.py
src/collective/saconnect/testing.py
src/collective/saconnect/browser/__init__.py
src/collective/saconnect/browser/configure.zcml
src/collective/saconnect/browser/panel.pt
src/collective/saconnect/browser/panel.py
src/collective/saconnect/browser/saconnect-icon.png
src/collective/saconnect/profiles/default/browserlayer.xml
src/collective/saconnect/profiles/default/controlpanel.xml
src/collective/saconnect/profiles/default/metadata.xml
src/collective/saconnect/tests/__init__.py
src/collective/saconnect/tests/test_gs.py
src/collective/saconnect/tests/test_setup.py