Metadata-Version: 1.1
Name: collective.saconnect
Version: 2.0.1
Summary: Plone Control Panel for SQL Alchemy connection strings
Home-page: http://pypi.python.org/pypi/collective.saconnect
Author: Plone Community (started by Jarn AS)
Author-email: info@jarn.com
License: GPL
Keywords: sqlalchemy plone zope2
Platform: UNKNOWN
Classifier: Programming Language :: Python
